{"preview":false,"result":{"api_path":"/addlocations","_time":"2025-12-01T11:10:00.000-0600","avg_sec_raw":"2.222","p95_sec_raw":"2.2220","p99_sec_raw":"2.2220","avg_sec":"2.2","current_p95_sec":"2.2","p95_sec":"2.2","p99_sec":"2.2","period_p95_avg":"2.2","trend_pct":"0.0"}}
{"preview":false,"result":{"api_path":"/getAvgMonthlyBill","_time":"2025-12-01T10:40:00.000-0600","avg_sec_raw":"12.468","p95_sec_raw":"12.468","p99_sec_raw":"12.468","avg_sec":"12.5","current_p95_sec":"12.5","p95_sec":"12.5","p99_sec":"12.5","period_p95_avg":"12.5","trend_pct":"0.0"}}
{"preview":false,"result":{"api_path":"/getOrderDateAvailability","_time":"2025-12-01T11:10:00.000-0600","avg_sec_raw":"4.989","p95_sec_raw":"4.9890","p99_sec_raw":"4.9890","avg_sec":"5.0","current_p95_sec":"5.3","p95_sec":"5.0","p99_sec":"5.0","period_p95_avg":"5.15","trend_pct":"2.9"}}
{"preview":false,"result":{"api_path":"/getOrderDateAvailability","_time":"2025-12-01T12:10:00.000-0600","avg_sec_raw":"4.68125","p95_sec_raw":"5.3462","p99_sec_raw":"5.3589","avg_sec":"4.7","current_p95_sec":"5.3","p95_sec":"5.3","p99_sec":"5.4","period_p95_avg":"5.15","trend_pct":"2.9"}}
{"preview":false,"result":{"api_path":"/getServiceOrderHistory","_time":"2025-12-01T10:40:00.000-0600","avg_sec_raw":"2.1025","p95_sec_raw":"2.5611","p99_sec_raw":"2.6018","avg_sec":"2.1","current_p95_sec":"1.6","p95_sec":"2.6","p99_sec":"2.6","period_p95_avg":"2.1","trend_pct":"-23.8"}}
{"preview":false,"result":{"api_path":"/getServiceOrderHistory","_time":"2025-12-01T12:10:00.000-0600","avg_sec_raw":"0.8635","p95_sec_raw":"1.55025","p99_sec_raw":"1.65645","avg_sec":"0.9","current_p95_sec":"1.6","p95_sec":"1.6","p99_sec":"1.7","period_p95_avg":"2.1","trend_pct":"-23.8"}}
{"preview":false,"result":{"api_path":"/getaddressautosuggest","_time":"2025-12-01T10:20:00.000-0600","avg_sec_raw":"3.44","p95_sec_raw":"3.4400","p99_sec_raw":"3.4400","avg_sec":"3.4","current_p95_sec":"1.2","p95_sec":"3.4","p99_sec":"3.4","period_p95_avg":"3.375","trend_pct":"-64.4"}}
{"preview":false,"result":{"api_path":"/getaddressautosuggest","_time":"2025-12-01T10:50:00.000-0600","avg_sec_raw":"1.550875","p95_sec_raw":"5.07355","p99_sec_raw":"6.17871","avg_sec":"1.6","current_p95_sec":"1.2","p95_sec":"5.1","p99_sec":"6.2","period_p95_avg":"3.375","trend_pct":"-64.4"}}
{"preview":false,"result":{"api_path":"/getaddressautosuggest","_time":"2025-12-01T11:00:00.000-0600","avg_sec_raw":"1.596","p95_sec_raw":"3.76620","p99_sec_raw":"4.14204","avg_sec":"1.6","current_p95_sec":"1.2","p95_sec":"3.8","p99_sec":"4.1","period_p95_avg":"3.375","trend_pct":"-64.4"}}
{"preview":false,"result":{"api_path":"/getaddressautosuggest","_time":"2025-12-01T11:10:00.000-0600","avg_sec_raw":"0.59475","p95_sec_raw":"1.16915","p99_sec_raw":"1.24343","avg_sec":"0.6","current_p95_sec":"1.2","p95_sec":"1.2","p99_sec":"1.2","period_p95_avg":"3.375","trend_pct":"-64.4"}}
{"preview":false,"result":{"api_path":"/getagreements","_time":"2025-11-30T14:30:00.000-0600","avg_sec_raw":"7.905","p95_sec_raw":"7.9050","p99_sec_raw":"7.9050","avg_sec":"7.9","current_p95_sec":"7.7","p95_sec":"7.9","p99_sec":"7.9","period_p95_avg":"6.818181818181819","trend_pct":"12.9"}}
{"preview":false,"result":{"api_path":"/getagreements","_time":"2025-11-30T20:30:00.000-0600","avg_sec_raw":"7.591","p95_sec_raw":"7.5910","p99_sec_raw":"7.5910","avg_sec":"7.6","current_p95_sec":"7.7","p95_sec":"7.6","p99_sec":"7.6","period_p95_avg":"6.818181818181819","trend_pct":"12.9"}}
{"preview":false,"result":{"api_path":"/getagreements","_time":"2025-12-01T08:10:00.000-0600","avg_sec_raw":"7.127","p95_sec_raw":"7.1270","p99_sec_raw":"7.1270","avg_sec":"7.1","current_p95_sec":"7.7","p95_sec":"7.1","p99_sec":"7.1","period_p95_avg":"6.818181818181819","trend_pct":"12.9"}}
{"preview":false,"result":{"api_path":"/getagreements","_time":"2025-12-01T09:30:00.000-0600","avg_sec_raw":"3.8776666666666664","p95_sec_raw":"6.7918","p99_sec_raw":"7.1920","avg_sec":"3.9","current_p95_sec":"7.7","p95_sec":"6.8","p99_sec":"7.2","period_p95_avg":"6.818181818181819","trend_pct":"12.9"}}
{"preview":false,"result":{"api_path":"/getagreements","_time":"2025-12-01T10:20:00.000-0600","avg_sec_raw":"4.622","p95_sec_raw":"7.0412","p99_sec_raw":"7.2562","avg_sec":"4.6","current_p95_sec":"7.7","p95_sec":"7.0","p99_sec":"7.3","period_p95_avg":"6.818181818181819","trend_pct":"12.9"}}
{"preview":false,"result":{"api_path":"/getagreements","_time":"2025-12-01T10:30:00.000-0600","avg_sec_raw":"7.567","p95_sec_raw":"7.5670","p99_sec_raw":"7.5670","avg_sec":"7.6","current_p95_sec":"7.7","p95_sec":"7.6","p99_sec":"7.6","period_p95_avg":"6.818181818181819","trend_pct":"12.9"}}
{"preview":false,"result":{"api_path":"/getagreements","_time":"2025-12-01T10:40:00.000-0600","avg_sec_raw":"4.266333333333334","p95_sec_raw":"6.9032","p99_sec_raw":"7.1814","avg_sec":"4.3","current_p95_sec":"7.7","p95_sec":"6.9","p99_sec":"7.2","period_p95_avg":"6.818181818181819","trend_pct":"12.9"}}
{"preview":false,"result":{"api_path":"/getagreements","_time":"2025-12-01T10:50:00.000-0600","avg_sec_raw":"7.655","p95_sec_raw":"7.6550","p99_sec_raw":"7.6550","avg_sec":"7.7","current_p95_sec":"7.7","p95_sec":"7.7","p99_sec":"7.7","period_p95_avg":"6.818181818181819","trend_pct":"12.9"}}
{"preview":false,"result":{"api_path":"/getagreements","_time":"2025-12-01T11:00:00.000-0600","avg_sec_raw":"2.5843333333333334","p95_sec_raw":"4.1380","p99_sec_raw":"4.3484","avg_sec":"2.6","current_p95_sec":"7.7","p95_sec":"4.1","p99_sec":"4.3","period_p95_avg":"6.818181818181819","trend_pct":"12.9"}}
{"preview":false,"result":{"api_path":"/getagreements","_time":"2025-12-01T11:10:00.000-0600","avg_sec_raw":"4.629","p95_sec_raw":"4.6290","p99_sec_raw":"4.6290","avg_sec":"4.6","current_p95_sec":"7.7","p95_sec":"4.6","p99_sec":"4.6","period_p95_avg":"6.818181818181819","trend_pct":"12.9"}}
{"preview":false,"result":{"api_path":"/getagreements","_time":"2025-12-01T11:40:00.000-0600","avg_sec_raw":"7.676","p95_sec_raw":"7.6760","p99_sec_raw":"7.6760","avg_sec":"7.7","current_p95_sec":"7.7","p95_sec":"7.7","p99_sec":"7.7","period_p95_avg":"6.818181818181819","trend_pct":"12.9"}}
{"preview":false,"result":{"api_path":"/getagreementsbypremisenumbers","_time":"2025-12-01T10:20:00.000-0600","avg_sec_raw":"3.9346666666666668","p95_sec_raw":"4.1217","p99_sec_raw":"4.1387","avg_sec":"3.9","current_p95_sec":"2.1","p95_sec":"4.1","p99_sec":"4.1","period_p95_avg":"3.0999999999999996","trend_pct":"-32.3"}}
{"preview":false,"result":{"api_path":"/getagreementsbypremisenumbers","_time":"2025-12-01T11:10:00.000-0600","avg_sec_raw":"1.0745833333333332","p95_sec_raw":"2.07205","p99_sec_raw":"2.17281","avg_sec":"1.1","current_p95_sec":"2.1","p95_sec":"2.1","p99_sec":"2.2","period_p95_avg":"3.0999999999999996","trend_pct":"-32.3"}}
{"preview":false,"result":{"api_path":"/getagreementsbyssn","_time":"2025-11-30T14:30:00.000-0600","avg_sec_raw":"5.9295","p95_sec_raw":"6.7607","p99_sec_raw":"6.8345","avg_sec":"5.9","current_p95_sec":"6.4","p95_sec":"6.8","p99_sec":"6.8","period_p95_avg":"6.6","trend_pct":"-3.0"}}
{"preview":false,"result":{"api_path":"/getagreementsbyssn","_time":"2025-12-01T11:00:00.000-0600","avg_sec_raw":"4.4502500000000005","p95_sec_raw":"6.3966","p99_sec_raw":"6.5377","avg_sec":"4.5","current_p95_sec":"6.4","p95_sec":"6.4","p99_sec":"6.5","period_p95_avg":"6.6","trend_pct":"-3.0"}}
{"preview":false,"result":{"api_path":"/getcoarsegrainedaddress","_time":"2025-12-01T10:20:00.000-0600","avg_sec_raw":"3.258","p95_sec_raw":"3.2580","p99_sec_raw":"3.2580","avg_sec":"3.3","current_p95_sec":"2.2","p95_sec":"3.3","p99_sec":"3.3","period_p95_avg":"2.875","trend_pct":"-23.5"}}
{"preview":false,"result":{"api_path":"/getcoarsegrainedaddress","_time":"2025-12-01T10:50:00.000-0600","avg_sec_raw":"1.87575","p95_sec_raw":"3.54905","p99_sec_raw":"3.84821","avg_sec":"1.9","current_p95_sec":"2.2","p95_sec":"3.5","p99_sec":"3.8","period_p95_avg":"2.875","trend_pct":"-23.5"}}
{"preview":false,"result":{"api_path":"/getcoarsegrainedaddress","_time":"2025-12-01T11:00:00.000-0600","avg_sec_raw":"0.9258571428571428","p95_sec_raw":"2.47020","p99_sec_raw":"3.06684","avg_sec":"0.9","current_p95_sec":"2.2","p95_sec":"2.5","p99_sec":"3.1","period_p95_avg":"2.875","trend_pct":"-23.5"}}
{"preview":false,"result":{"api_path":"/getcoarsegrainedaddress","_time":"2025-12-01T11:10:00.000-0600","avg_sec_raw":"1.0972000000000002","p95_sec_raw":"2.18240","p99_sec_raw":"2.40288","avg_sec":"1.1","current_p95_sec":"2.2","p95_sec":"2.2","p99_sec":"2.4","period_p95_avg":"2.875","trend_pct":"-23.5"}}
{"preview":false,"result":{"api_path":"/getlocations","_time":"2025-11-30T14:30:00.000-0600","avg_sec_raw":"4.804","p95_sec_raw":"4.8040","p99_sec_raw":"4.8040","avg_sec":"4.8","current_p95_sec":"6.7","p95_sec":"4.8","p99_sec":"4.8","period_p95_avg":"5.214285714285715","trend_pct":"28.5"}}
{"preview":false,"result":{"api_path":"/getlocations","_time":"2025-11-30T16:20:00.000-0600","avg_sec_raw":"6.977","p95_sec_raw":"6.9770","p99_sec_raw":"6.9770","avg_sec":"7.0","current_p95_sec":"6.7","p95_sec":"7.0","p99_sec":"7.0","period_p95_avg":"5.214285714285715","trend_pct":"28.5"}}
{"preview":false,"result":{"api_path":"/getlocations","_time":"2025-11-30T20:30:00.000-0600","avg_sec_raw":"4.981","p95_sec_raw":"4.9810","p99_sec_raw":"4.9810","avg_sec":"5.0","current_p95_sec":"6.7","p95_sec":"5.0","p99_sec":"5.0","period_p95_avg":"5.214285714285715","trend_pct":"28.5"}}
{"preview":false,"result":{"api_path":"/getlocations","_time":"2025-11-30T21:00:00.000-0600","avg_sec_raw":"7.155","p95_sec_raw":"7.1550","p99_sec_raw":"7.1550","avg_sec":"7.2","current_p95_sec":"6.7","p95_sec":"7.2","p99_sec":"7.2","period_p95_avg":"5.214285714285715","trend_pct":"28.5"}}
{"preview":false,"result":{"api_path":"/getlocations","_time":"2025-11-30T21:10:00.000-0600","avg_sec_raw":"4.262","p95_sec_raw":"6.5742","p99_sec_raw":"6.8428","avg_sec":"4.3","current_p95_sec":"6.7","p95_sec":"6.6","p99_sec":"6.8","period_p95_avg":"5.214285714285715","trend_pct":"28.5"}}
{"preview":false,"result":{"api_path":"/getlocations","_time":"2025-11-30T21:20:00.000-0600","avg_sec_raw":"2.218","p95_sec_raw":"2.2180","p99_sec_raw":"2.2180","avg_sec":"2.2","current_p95_sec":"6.7","p95_sec":"2.2","p99_sec":"2.2","period_p95_avg":"5.214285714285715","trend_pct":"28.5"}}
{"preview":false,"result":{"api_path":"/getlocations","_time":"2025-11-30T21:40:00.000-0600","avg_sec_raw":"6.856","p95_sec_raw":"6.8560","p99_sec_raw":"6.8560","avg_sec":"6.9","current_p95_sec":"6.7","p95_sec":"6.9","p99_sec":"6.9","period_p95_avg":"5.214285714285715","trend_pct":"28.5"}}
{"preview":false,"result":{"api_path":"/getlocations","_time":"2025-11-30T22:00:00.000-0600","avg_sec_raw":"6.831","p95_sec_raw":"6.8310","p99_sec_raw":"6.8310","avg_sec":"6.8","current_p95_sec":"6.7","p95_sec":"6.8","p99_sec":"6.8","period_p95_avg":"5.214285714285715","trend_pct":"28.5"}}
{"preview":false,"result":{"api_path":"/getlocations","_time":"2025-12-01T08:10:00.000-0600","avg_sec_raw":"4.808","p95_sec_raw":"4.8080","p99_sec_raw":"4.8080","avg_sec":"4.8","current_p95_sec":"6.7","p95_sec":"4.8","p99_sec":"4.8","period_p95_avg":"5.214285714285715","trend_pct":"28.5"}}
{"preview":false,"result":{"api_path":"/getlocations","_time":"2025-12-01T08:50:00.000-0600","avg_sec_raw":"6.557","p95_sec_raw":"6.5570","p99_sec_raw":"6.5570","avg_sec":"6.6","current_p95_sec":"6.7","p95_sec":"6.6","p99_sec":"6.6","period_p95_avg":"5.214285714285715","trend_pct":"28.5"}}
{"preview":false,"result":{"api_path":"/getlocations","_time":"2025-12-01T09:30:00.000-0600","avg_sec_raw":"3.285","p95_sec_raw":"4.6347","p99_sec_raw":"4.8205","avg_sec":"3.3","current_p95_sec":"6.7","p95_sec":"4.6","p99_sec":"4.8","period_p95_avg":"5.214285714285715","trend_pct":"28.5"}}
{"preview":false,"result":{"api_path":"/getlocations","_time":"2025-12-01T10:00:00.000-0600","avg_sec_raw":"6.889","p95_sec_raw":"6.8890","p99_sec_raw":"6.8890","avg_sec":"6.9","current_p95_sec":"6.7","p95_sec":"6.9","p99_sec":"6.9","period_p95_avg":"5.214285714285715","trend_pct":"28.5"}}
{"preview":false,"result":{"api_path":"/getlocations","_time":"2025-12-01T10:20:00.000-0600","avg_sec_raw":"3.7675","p95_sec_raw":"4.9019","p99_sec_raw":"5.0028","avg_sec":"3.8","current_p95_sec":"6.7","p95_sec":"4.9","p99_sec":"5.0","period_p95_avg":"5.214285714285715","trend_pct":"28.5"}}
{"preview":false,"result":{"api_path":"/getlocations","_time":"2025-12-01T10:30:00.000-0600","avg_sec_raw":"4.723","p95_sec_raw":"4.7230","p99_sec_raw":"4.7230","avg_sec":"4.7","current_p95_sec":"6.7","p95_sec":"4.7","p99_sec":"4.7","period_p95_avg":"5.214285714285715","trend_pct":"28.5"}}
{"preview":false,"result":{"api_path":"/getlocations","_time":"2025-12-01T10:40:00.000-0600","avg_sec_raw":"2.4624999999999995","p95_sec_raw":"4.31050","p99_sec_raw":"4.54210","avg_sec":"2.5","current_p95_sec":"6.7","p95_sec":"4.3","p99_sec":"4.5","period_p95_avg":"5.214285714285715","trend_pct":"28.5"}}
{"preview":false,"result":{"api_path":"/getlocations","_time":"2025-12-01T10:50:00.000-0600","avg_sec_raw":"2.4160000000000004","p95_sec_raw":"2.7913","p99_sec_raw":"2.8247","avg_sec":"2.4","current_p95_sec":"6.7","p95_sec":"2.8","p99_sec":"2.8","period_p95_avg":"5.214285714285715","trend_pct":"28.5"}}
{"preview":false,"result":{"api_path":"/getlocations","_time":"2025-12-01T11:00:00.000-0600","avg_sec_raw":"2.017","p95_sec_raw":"2.96740","p99_sec_raw":"3.05188","avg_sec":"2.0","current_p95_sec":"6.7","p95_sec":"3.0","p99_sec":"3.1","period_p95_avg":"5.214285714285715","trend_pct":"28.5"}}
{"preview":false,"result":{"api_path":"/getlocations","_time":"2025-12-01T11:10:00.000-0600","avg_sec_raw":"1.5005","p95_sec_raw":"2.14355","p99_sec_raw":"2.20071","avg_sec":"1.5","current_p95_sec":"6.7","p95_sec":"2.1","p99_sec":"2.2","period_p95_avg":"5.214285714285715","trend_pct":"28.5"}}
{"preview":false,"result":{"api_path":"/getlocations","_time":"2025-12-01T11:20:00.000-0600","avg_sec_raw":"6.694","p95_sec_raw":"6.6940","p99_sec_raw":"6.6940","avg_sec":"6.7","current_p95_sec":"6.7","p95_sec":"6.7","p99_sec":"6.7","period_p95_avg":"5.214285714285715","trend_pct":"28.5"}}
{"preview":false,"result":{"api_path":"/getlocations","_time":"2025-12-01T11:40:00.000-0600","avg_sec_raw":"4.887","p95_sec_raw":"4.8870","p99_sec_raw":"4.8870","avg_sec":"4.9","current_p95_sec":"6.7","p95_sec":"4.9","p99_sec":"4.9","period_p95_avg":"5.214285714285715","trend_pct":"28.5"}}
{"preview":false,"result":{"api_path":"/getlocations","_time":"2025-12-01T12:10:00.000-0600","avg_sec_raw":"5.772","p95_sec_raw":"6.6504","p99_sec_raw":"6.7285","avg_sec":"5.8","current_p95_sec":"6.7","p95_sec":"6.7","p99_sec":"6.7","period_p95_avg":"5.214285714285715","trend_pct":"28.5"}}
{"preview":false,"result":{"api_path":"/removelocations","_time":"2025-12-01T10:20:00.000-0600","avg_sec_raw":"2.863","p95_sec_raw":"2.8630","p99_sec_raw":"2.8630","avg_sec":"2.9","current_p95_sec":"1.6","p95_sec":"2.9","p99_sec":"2.9","period_p95_avg":"2.4250000000000003","trend_pct":"-34.0"}}
{"preview":false,"result":{"api_path":"/removelocations","_time":"2025-12-01T10:50:00.000-0600","avg_sec_raw":"3.024","p95_sec_raw":"3.0240","p99_sec_raw":"3.0240","avg_sec":"3.0","current_p95_sec":"1.6","p95_sec":"3.0","p99_sec":"3.0","period_p95_avg":"2.4250000000000003","trend_pct":"-34.0"}}
{"preview":false,"result":{"api_path":"/removelocations","_time":"2025-12-01T11:00:00.000-0600","avg_sec_raw":"2.166","p95_sec_raw":"2.1660","p99_sec_raw":"2.1660","avg_sec":"2.2","current_p95_sec":"1.6","p95_sec":"2.2","p99_sec":"2.2","period_p95_avg":"2.4250000000000003","trend_pct":"-34.0"}}
{"preview":false,"result":{"api_path":"/removelocations","_time":"2025-12-01T11:10:00.000-0600","avg_sec_raw":"1.563","p95_sec_raw":"1.5630","p99_sec_raw":"1.5630","avg_sec":"1.6","current_p95_sec":"1.6","p95_sec":"1.6","p99_sec":"1.6","period_p95_avg":"2.4250000000000003","trend_pct":"-34.0"}}
{"preview":false,"result":{"api_path":"/sendEmailUpdateEmail","_time":"2025-12-01T11:00:00.000-0600","avg_sec_raw":"4.47325","p95_sec_raw":"5.0641","p99_sec_raw":"5.1152","avg_sec":"4.5","current_p95_sec":"5.1","p95_sec":"5.1","p99_sec":"5.1","period_p95_avg":"5.1","trend_pct":"0.0"}}
{"preview":false,"result":{"api_path":"/sendRegistrationConfirmationEmail","_time":"2025-12-01T11:00:00.000-0600","avg_sec_raw":"2.53","p95_sec_raw":"3.5749","p99_sec_raw":"3.6678","avg_sec":"2.5","current_p95_sec":"3.6","p95_sec":"3.6","p99_sec":"3.7","period_p95_avg":"3.6","trend_pct":"0.0"}}
{"preview":false,"result":{"api_path":"/updateAgreement","_time":"2025-12-01T11:00:00.000-0600","avg_sec_raw":"10.070500000000001","p95_sec_raw":"15.3789","p99_sec_raw":"15.7398","avg_sec":"10.1","current_p95_sec":"15.4","p95_sec":"15.4","p99_sec":"15.7","period_p95_avg":"15.4","trend_pct":"0.0"}}
{"preview":false,"result":{"api_path":"/updateUserCommAndReports","_time":"2025-12-01T11:00:00.000-0600","avg_sec_raw":"4.32225","p95_sec_raw":"5.0779","p99_sec_raw":"5.1468","avg_sec":"4.3","current_p95_sec":"5.1","p95_sec":"5.1","p99_sec":"5.1","period_p95_avg":"5.1","trend_pct":"0.0"}}
{"preview":false,"lastrow":true,"result":{"api_path":"/updateuseragreementsinfr","_time":"2025-12-01T11:00:00.000-0600","avg_sec_raw":"4.4014999999999995","p95_sec_raw":"6.2173","p99_sec_raw":"6.3786","avg_sec":"4.4","current_p95_sec":"6.2","p95_sec":"6.2","p99_sec":"6.4","period_p95_avg":"6.2","trend_pct":"0.0"}}
